{
  "_id": "9e46a2f5b90703bf",
  "name": "Babelion Espectro Oscuro Menor",
  "type": "character",
  "img": "icons/svg/mystery-man.svg",
  "prototypeToken": {
    "name": "Babelion Espectro Oscuro Menor"
  },
  "items": [],
  "effects": [],
  "folder": null,
  "sort": 0,
  "flags": {
    "animu-exxet": {
      "sourceBook": "Anima Pantalla del Director",
      "sourceHeading": "Babelion Espectro Oscuro Menor",
      "page": 32,
      "variant": null,
      "rawClass": "Ánima, elemental 15",
      "rawDamage": "40 Garras lóbregas FIL",
      "rawTA": null,
      "warnings": []
    }
  },
  "system": {
    "version": 0,
    "ui": {
      "contractibleItems": {},
      "tabVisibility": {
        "mystic": {
          "value": false
        },
        "domine": {
          "value": false
        },
        "psychic": {
          "value": false
        },
        "effects": {
          "value": false
        }
      }
    },
    "automationOptions": {
      "calculateFatigueModifier": {
        "value": true
      }
    },
    "general": {
      "settings": {
        "openRolls": {
          "value": 90
        },
        "fumbles": {
          "value": 3
        },
        "openOnDoubles": {
          "value": false
        },
        "perceiveMystic": {
          "value": false
        },
        "perceivePsychic": {
          "value": false
        },
        "inmaterial": {
          "value": true
        },
        "inhuman": {
          "value": false
        },
        "zen": {
          "value": false
        },
        "defenseType": {
          "value": ""
        }
      },
      "diceSettings": {
        "characteristicDie": {
          "value": "1d10ControlRoll"
        },
        "initiativeDie": {
          "value": "1d100Initiative"
        },
        "resistanceDie": {
          "value": "1d100"
        },
        "abilityDie": {
          "value": "1d100xa"
        },
        "abilityMasteryDie": {
          "value": "1d100xamastery"
        }
      },
      "modifiers": {
        "physicalActions": {
          "base": {
            "value": 0
          },
          "special": {
            "value": 0
          },
          "final": {
            "value": 0
          }
        },
        "allActions": {
          "base": {
            "value": 0
          },
          "special": {
            "value": 0
          },
          "final": {
            "value": 0
          }
        },
        "naturalPenalty": {
          "unreduced": {
            "value": 0
          },
          "reduction": {
            "value": 0
          },
          "base": {
            "value": 0
          },
          "special": {
            "value": 0
          },
          "final": {
            "value": 0
          }
        },
        "perceptionPenalty": {
          "base": {
            "value": 0
          },
          "special": {
            "value": 0
          },
          "final": {
            "value": 0
          }
        },
        "extraDamage": {
          "__type": "{\"type\":\"NumericalValue\"}"
        },
        "automaticCrit": {
          "value": false
        },
        "critDamageBonus": {
          "__type": "{\"type\":\"NumericalValue\"}"
        }
      },
      "destinyPoints": {
        "base": {
          "value": 0
        },
        "final": {
          "value": 0
        }
      },
      "presence": {
        "base": {
          "value": 0
        },
        "special": {
          "value": 0
        },
        "final": {
          "value": 0
        }
      },
      "aspect": {
        "hair": {
          "value": ""
        },
        "eyes": {
          "value": ""
        },
        "height": {
          "value": ""
        },
        "weight": {
          "value": ""
        },
        "age": {
          "value": ""
        },
        "gender": {
          "value": ""
        },
        "race": {
          "value": "Ánima, elemental 15"
        },
        "ethnicity": {
          "value": ""
        },
        "appearance": {
          "value": ""
        },
        "size": {
          "value": 12
        }
      },
      "advantages": [],
      "contacts": [],
      "inventory": [],
      "money": {
        "cooper": {
          "value": 0
        },
        "silver": {
          "value": 0
        },
        "gold": {
          "value": 0
        }
      },
      "description": {
        "value": "<section><h2>Fuente</h2><p><strong>Fuente:</strong> Anima Pantalla del Director</p><p><strong>Página:</strong> 32</p><p><strong>Entrada:</strong> Babelion Espectro Oscuro Menor</p></section><section><h2>Resumen importado</h2><p><strong>Clase:</strong> Ánima, elemental 15</p><p><strong>Categoría:</strong> Asesino Fue: 5 Des: 8 Agi: 8 Con: -- Pod: 6 Int: 6 Vol: 6 Per: 8 RF 35 RM 35 RP 35 RV 35 RE 35</p><p><strong>Habilidades esenciales:</strong> Exención física.</p><p><strong>Poderes:</strong> Armas naturales; Garras lóbregas (Efecto místico añadido: Dolor), Forma sellada, Interacción con el mundo, Visión nocturna.</p><p><strong>Daño:</strong> 40 Garras lóbregas FIL</p><p><strong>Habilidades secundarias:</strong> Trepar 20, Ocultarse 45, Sigilo 50, Advertir 40, Buscar 30, Intimidar 15, Frialdad 25</p><p><strong>Descripción breve:</strong> Babelion es una tipología de espíritu oscuro menor, que surge en los lugares de la Vigilia en los que los niños han sufrido mucho. Habitualmente no moran en el mundo material, pero en extrañas ocasiones son atraídas a nuestra realidad por el dolor de los infantes. No son esencialmente malignos, pero les disgustan mucho los adultos que maltratan a las personas indefensas. Si se encuentran con esta clase de individuos, disfrutan matándolos de la manera más dolorosa que pueden. Yciertamente, son bastante imaginativos a la hora de matar... Habitualmente se encuentran bajo la forma de algún pequeño animalito inofensivo y de aspecto simpático, que sólo los niños, visionarios y locos pueden ver. No obstante, su verdadero aspecto es el de una nube de humo con un rostro esquelético y dos largas extremidades acabadas en funestas garras. Cuando se manifiestan en el mundo, vagan caóticamente sin permanecer mucho tiempo en un lugar, aunque a veces se encariñan con algún pequeño que logra verlos y se quedan con él durante un tiempo prolongado. De hecho, frecuentemente los “amigos invisibles” que tienen algunos niños son, en realidad, Babelions. Cuando sus compañeros crecen y dejan de verlos, se marchan en busca de otro lugar en el que permanecer una temporada. Anecdóticamente, odian a los gatos, y los rehuyen siempre que les sea posible. Babe, el espíritu que se encuentra al servicio de Lamya, ha estado con ella desde que era una niña, y en consecuencia se ha encariñado de su señora. Toma la forma de un pequeño dragoncito negro, y sólo cuando su dueña le ordena transformarse y liberar todo su poder, recupera su apariencia real. A pesar de su atadura y dominación, acepta de buena ganas casi todas las ordenes que recibe, ya que no suelen ir en contra de su naturaleza. m oDus operanDi Los Babelion no tienen una metodología de acción común y cada uno emplea sus propios métodos para acercarse a la gente, aunque lo más normal es que usen sus buenas dotes de subterfugio. Habitualmente pasan todo el tiempo bajo su forma más inofensiva, y sólo liberan su poder cuando van a entrar en combate. Dado que son virtualmente invulnerables salvo contra ataques sobrenaturales, resulta muy difícil destruirlos completamente. Como elementales oscuros, sufren un daño incrementado ante los ataques basados en luz. No tienen ningún punto vulnerable en ninguna de sus dos formas. Forma sellada: Mientras permanecen bajo su forma sellada, los Babelion son invisibles para cualquier persona normal. Sólo los niños, y aquellos que puedan ver criaturas espirituales, son capaces de percibirlos. Del mismo modo, resultan inmunes a cualquier ataque convencional que no sea capaz de dañar energía. Forma real: En su forma real pierden su invisibilidad, y pueden ser vistos por cualquiera como una espesa nube de humo. Aun así, siguen siendo esencialmente invulnerables a los ataques convencionales. Los Babelion no pueden adoptar su forma real en lugares muy iluminados. Garras lóbregas: A pesar de su inmaterialidad, un Babelion puede usar sus garras para atacar a blancos corpóreos con completa normalidad. Son equivalentes a un arma de Filo con Rotura 0. Adicionalmente, el contacto con ellas produce un terrible sufrimiento espiritual, por lo que cualquiera que reciba sus daños debe superar una RF contra 60 o se verá sometido al estado de Dolor. Sólo pueden usar las Garras lóbregas si se encuentran en su forma real. #### Vladimir Nux _Página 33_ JinChaoLan</p></section><details><summary>Texto extraído</summary><pre>Nivel: 1\n\nClase: Ánima, elemental 1 5 Puntos de Vida: 90 Categoría: Asesino Fue: 5 Des: 8 Agi: 8 Con: -- Pod: 6 Int: 6 Vol: 6 Per: 8 RF 35 RM 35 RP 35 RV 35 RE 35\n\nTurno: 70 Natural Habilidad de ataque: 65 Garras lóbregas Habilidad de defensa: 60 Esquiva Daño: 40 Garras lóbregas FILHabilidades esenciales: Exención física. Poderes: Armas naturales; Garras lóbregas (Efecto místico añadido: Dolor), Forma sellada, Interacción con el mundo, Visión nocturna.\n\nTamaño: 12 Medio (Var.) Regeneración: 1 Tipo de movimiento: 8 Cansancio: Incansable Habilidades Secundarias: Trepar 20, Ocultarse 45, Sigilo 50, Advertir 40, Buscar 30, Intimidar 1 5, Frialdad 25. Babelion es una tipología de espíritu oscuro menor, que surge en los lugares de la Vigilia en los que los niños han sufrido mucho. Habitualmente no moran en el mundo material, pero en extrañas ocasiones son atraídas a nuestra realidad por el dolor de los infantes. No son esencialmente malignos, pero les disgustan mucho los adultos que maltratan a las personas indefensas. Si se encuentran con esta clase de individuos, disfrutan matándolos de la manera más dolorosa que pueden. Yciertamente, son bastante imaginativos a la hora de matar... Habitualmente se encuentran bajo la forma de algún pequeño animalito inofensivo y de aspecto simpático, que sólo los niños, visionarios y locos pueden ver.\n\nNo obstante, su verdadero aspecto es el de una nube de humo con un rostro esquelético y dos largas extremidades acabadas en funestas garras. Cuando se manifiestan en el mundo, vagan caóticamente sin permanecer mucho tiempo en un lugar, aunque a veces se encariñan con algún pequeño que logra verlos y se quedan con él durante un tiempo prolongado. De hecho, frecuentemente los “amigos invisibles” que tienen algunos niños son, en realidad, Babelions. Cuando sus compañeros crecen y dejan de verlos, se marchan en busca de otro lugar en el que permanecer una temporada. Anecdóticamente, odian a los gatos, y los rehuyen siempre que les sea posible. Babe, el espíritu que se encuentra al servicio de Lamya, ha estado con ella desde que era una niña, y en consecuencia se ha encariñado de su señora.\n\nToma la forma de un pequeño dragoncito negro, y sólo cuando su dueña le ordena transformarse y liberar todo su poder, recupera su apariencia real. A pesar de su atadura y dominación, acepta de buena ganas casi todas las ordenes que recibe, ya que no suelen ir en contra de su naturaleza. m oDus operanDi Los Babelion no tienen una metodología de acción común y cada uno emplea sus propios métodos para acercarse a la gente, aunque lo más normal es que usen sus buenas dotes de subterfugio. Habitualmente pasan todo el tiempo bajo su forma más inofensiva, y sólo liberan su poder cuando van a entrar en combate. Dado que son virtualmente invulnerables salvo contra ataques sobrenaturales, resulta muy difícil destruirlos completamente. Como elementales oscuros, sufren un daño incrementado ante los ataques basados en luz. No tienen ningún punto vulnerable en ninguna de sus dos formas.\n\nForma sellada: Mientras permanecen bajo su forma sellada, los Babelion son invisibles para cualquier persona normal. Sólo los niños, y aquellos que puedan ver criaturas espirituales, son capaces de percibirlos. Del mismo modo, resultan inmunes a cualquier ataque convencional que no sea capaz de dañar energía. Forma real: En su forma real pierden su invisibilidad, y pueden ser vistos por cualquiera como una espesa nube de humo. Aun así, siguen siendo esencialmente invulnerables a los ataques convencionales. Los Babelion no pueden adoptar su forma real en lugares muy iluminados. Garras lóbregas: A pesar de su inmaterialidad, un Babelion puede usar sus garras para atacar a blancos corpóreos con completa normalidad. Son equivalentes a un arma de Filo con Rotura 0.\n\nAdicionalmente, el contacto con ellas produce un terrible sufrimiento espiritual, por lo que cualquiera que reciba sus daños debe superar una RF contra 60 o se verá sometido al estado de Dolor. Sólo pueden usar las Garras lóbregas si se encuentran en su forma real.\n\n#### Vladimir Nux\n\n&lt;!-- tags: @conjuro, @psiquico, @regla --&gt;\n\n_Página 33_\n\nJinChaoLan</pre></details>"
      },
      "disadvantages": [],
      "elan": [],
      "experience": {
        "current": {
          "value": 0
        },
        "next": {
          "value": 0
        }
      },
      "languages": {
        "base": {
          "value": ""
        },
        "others": []
      },
      "levels": [
        {
          "_id": "lvl-babelion-espectro-oscuro",
          "type": "level",
          "name": "Babelion Espectro Oscuro Menor",
          "flags": {
            "version": 1
          },
          "system": {
            "level": 1
          }
        }
      ],
      "level": {
        "value": 1
      },
      "notes": [
        {
          "_id": "note-babelion-espectro-oscuro-menor-3",
          "type": "note",
          "name": "Habilidades esenciales: Exención física.",
          "system": {}
        },
        {
          "_id": "note-babelion-espectro-oscuro-menor-4",
          "type": "note",
          "name": "Poderes: Armas naturales; Garras lóbregas (Efecto místico añadido: Dolor), Forma sellada, Interacción con el mundo, Visión nocturna.",
          "system": {}
        }
      ],
      "titles": []
    },
    "characteristics": {
      "primaries": {
        "agility": {
          "__type": "{\"type\":\"Characteristic\"}",
          "base": {
            "value": 8
          }
        },
        "constitution": {
          "__type": "{\"type\":\"Characteristic\"}",
          "base": {
            "value": 0
          }
        },
        "dexterity": {
          "__type": "{\"type\":\"Characteristic\"}",
          "base": {
            "value": 8
          }
        },
        "strength": {
          "__type": "{\"type\":\"Characteristic\"}",
          "base": {
            "value": 5
          }
        },
        "intelligence": {
          "__type": "{\"type\":\"Characteristic\"}",
          "base": {
            "value": 6
          }
        },
        "perception": {
          "__type": "{\"type\":\"Characteristic\"}",
          "base": {
            "value": 8
          }
        },
        "power": {
          "__type": "{\"type\":\"Characteristic\"}",
          "base": {
            "value": 6
          }
        },
        "willPower": {
          "__type": "{\"type\":\"Characteristic\"}",
          "base": {
            "value": 6
          }
        }
      },
      "secondaries": {
        "lifePoints": {
          "value": 90,
          "max": 90
        },
        "initiative": {
          "base": {
            "value": 70
          },
          "special": {
            "value": 0
          },
          "final": {
            "value": 0
          }
        },
        "fatigue": {
          "value": 0,
          "max": 0
        },
        "regenerationType": {
          "mod": {
            "value": 1
          },
          "final": {
            "value": 0
          }
        },
        "regeneration": {
          "normal": {
            "value": 0,
            "period": ""
          },
          "resting": {
            "value": 0,
            "period": ""
          },
          "recovery": {
            "value": 0,
            "period": ""
          }
        },
        "movementType": {
          "mod": {
            "value": 0
          },
          "final": {
            "value": 0
          }
        },
        "movement": {
          "maximum": {
            "value": 0
          },
          "running": {
            "value": 0
          }
        },
        "resistances": {
          "physical": {
            "base": {
              "value": 0
            },
            "special": {
              "value": 5
            },
            "final": {
              "value": 0
            }
          },
          "disease": {
            "base": {
              "value": 0
            },
            "special": {
              "value": 5
            },
            "final": {
              "value": 0
            }
          },
          "poison": {
            "base": {
              "value": 0
            },
            "special": {
              "value": 3540
            },
            "final": {
              "value": 0
            }
          },
          "magic": {
            "base": {
              "value": 0
            },
            "special": {
              "value": 0
            },
            "final": {
              "value": 0
            }
          },
          "psychic": {
            "base": {
              "value": 0
            },
            "special": {
              "value": 0
            },
            "final": {
              "value": 0
            }
          }
        }
      }
    },
    "secondaries": {
      "athletics": {
        "acrobatics": {
          "__type": "{\"type\":\"SecondaryAbility\",\"attribute\":\"agility\",\"applyNaturalPenalty\":\"true\"}"
        },
        "athleticism": {
          "__type": "{\"type\":\"SecondaryAbility\",\"attribute\":\"agility\",\"applyNaturalPenalty\":\"true\"}"
        },
        "ride": {
          "__type": "{\"type\":\"SecondaryAbility\",\"attribute\":\"agility\"}"
        },
        "swim": {
          "__type": "{\"type\":\"SecondaryAbility\",\"attribute\":\"agility\",\"applyNaturalPenalty\":\"true\",\"maxNaturalPenaltyReductionPercentage\":\"0\"}"
        },
        "climb": {
          "__type": "{\"type\":\"SecondaryAbility\",\"attribute\":\"agility\",\"applyNaturalPenalty\":\"true\"}",
          "base": {
            "value": 20
          }
        },
        "jump": {
          "__type": "{\"type\":\"SecondaryAbility\",\"attribute\":\"strength\",\"applyNaturalPenalty\":\"true\"}"
        },
        "piloting": {
          "__type": "{\"type\":\"SecondaryAbility\",\"attribute\":\"dexterity\"}"
        }
      },
      "vigor": {
        "composure": {
          "__type": "{\"type\":\"SecondaryAbility\",\"attribute\":\"willPower\"}",
          "base": {
            "value": 25
          }
        },
        "featsOfStrength": {
          "__type": "{\"type\":\"SecondaryAbility\",\"attribute\":\"strength\",\"applyNaturalPenalty\":\"true\"}"
        },
        "withstandPain": {
          "__type": "{\"type\":\"SecondaryAbility\",\"attribute\":\"willPower\"}"
        }
      },
      "perception": {
        "notice": {
          "__type": "{\"type\":\"SecondaryAbility\",\"attribute\":\"perception\",\"applyPerceptionPenalty\":\"true\"}",
          "base": {
            "value": 40
          }
        },
        "search": {
          "__type": "{\"type\":\"SecondaryAbility\",\"attribute\":\"perception\",\"applyPerceptionPenalty\":\"true\"}",
          "base": {
            "value": 30
          }
        },
        "track": {
          "__type": "{\"type\":\"SecondaryAbility\",\"attribute\":\"perception\"}"
        }
      },
      "intellectual": {
        "animals": {
          "__type": "{\"type\":\"SecondaryAbility\",\"attribute\":\"intelligence\"}"
        },
        "science": {
          "__type": "{\"type\":\"SecondaryAbility\",\"attribute\":\"intelligence\"}"
        },
        "law": {
          "__type": "{\"type\":\"SecondaryAbility\",\"attribute\":\"intelligence\"}"
        },
        "herbalLore": {
          "__type": "{\"type\":\"SecondaryAbility\",\"attribute\":\"intelligence\"}"
        },
        "history": {
          "__type": "{\"type\":\"SecondaryAbility\",\"attribute\":\"intelligence\"}"
        },
        "tactics": {
          "__type": "{\"type\":\"SecondaryAbility\",\"attribute\":\"intelligence\"}"
        },
        "medicine": {
          "__type": "{\"type\":\"SecondaryAbility\",\"attribute\":\"intelligence\"}"
        },
        "memorize": {
          "__type": "{\"type\":\"SecondaryAbility\",\"attribute\":\"intelligence\"}"
        },
        "navigation": {
          "__type": "{\"type\":\"SecondaryAbility\",\"attribute\":\"intelligence\"}"
        },
        "occult": {
          "__type": "{\"type\":\"SecondaryAbility\",\"attribute\":\"intelligence\"}"
        },
        "appraisal": {
          "__type": "{\"type\":\"SecondaryAbility\",\"attribute\":\"intelligence\"}"
        },
        "magicAppraisal": {
          "__type": "{\"type\":\"SecondaryAbility\",\"attribute\":\"power\"}"
        }
      },
      "social": {
        "style": {
          "__type": "{\"type\":\"SecondaryAbility\",\"attribute\":\"power\"}"
        },
        "intimidate": {
          "__type": "{\"type\":\"SecondaryAbility\",\"attribute\":\"willPower\"}",
          "base": {
            "value": 15
          }
        },
        "leadership": {
          "__type": "{\"type\":\"SecondaryAbility\",\"attribute\":\"power\"}"
        },
        "persuasion": {
          "__type": "{\"type\":\"SecondaryAbility\",\"attribute\":\"intelligence\"}"
        },
        "trading": {
          "__type": "{\"type\":\"SecondaryAbility\",\"attribute\":\"intelligence\"}"
        },
        "streetwise": {
          "__type": "{\"type\":\"SecondaryAbility\",\"attribute\":\"intelligence\"}"
        },
        "etiquette": {
          "__type": "{\"type\":\"SecondaryAbility\",\"attribute\":\"intelligence\"}"
        }
      },
      "subterfuge": {
        "lockPicking": {
          "__type": "{\"type\":\"SecondaryAbility\",\"attribute\":\"dexterity\"}"
        },
        "disguise": {
          "__type": "{\"type\":\"SecondaryAbility\",\"attribute\":\"dexterity\"}"
        },
        "hide": {
          "__type": "{\"type\":\"SecondaryAbility\",\"attribute\":\"perception\",\"applyNaturalPenalty\":\"true\"}",
          "base": {
            "value": 45
          }
        },
        "theft": {
          "__type": "{\"type\":\"SecondaryAbility\",\"attribute\":\"dexterity\"}"
        },
        "stealth": {
          "__type": "{\"type\":\"SecondaryAbility\",\"attribute\":\"agility\",\"applyNaturalPenalty\":\"true\",\"maxNaturalPenaltyReductionPercentage\":\"50\"}",
          "base": {
            "value": 50
          }
        },
        "trapLore": {
          "__type": "{\"type\":\"SecondaryAbility\",\"attribute\":\"dexterity\"}"
        },
        "poisons": {
          "__type": "{\"type\":\"SecondaryAbility\",\"attribute\":\"intelligence\"}"
        }
      },
      "creative": {
        "art": {
          "__type": "{\"type\":\"SecondaryAbility\",\"attribute\":\"power\"}"
        },
        "dance": {
          "__type": "{\"type\":\"SecondaryAbility\",\"attribute\":\"agility\",\"applyNaturalPenalty\":\"true\"}"
        },
        "forging": {
          "__type": "{\"type\":\"SecondaryAbility\",\"attribute\":\"dexterity\"}"
        },
        "runes": {
          "__type": "{\"type\":\"SecondaryAbility\",\"attribute\":\"dexterity\"}"
        },
        "alchemy": {
          "__type": "{\"type\":\"SecondaryAbility\",\"attribute\":\"intelligence\"}"
        },
        "animism": {
          "__type": "{\"type\":\"SecondaryAbility\",\"attribute\":\"power\"}"
        },
        "music": {
          "__type": "{\"type\":\"SecondaryAbility\",\"attribute\":\"power\"}"
        },
        "sleightOfHand": {
          "__type": "{\"type\":\"SecondaryAbility\",\"attribute\":\"dexterity\"}"
        },
        "ritualCalligraphy": {
          "__type": "{\"type\":\"SecondaryAbility\",\"attribute\":\"dexterity\"}"
        },
        "jewelry": {
          "__type": "{\"type\":\"SecondaryAbility\",\"attribute\":\"dexterity\"}"
        },
        "tailoring": {
          "__type": "{\"type\":\"SecondaryAbility\",\"attribute\":\"dexterity\"}"
        },
        "puppetMaking": {
          "__type": "{\"type\":\"SecondaryAbility\",\"attribute\":\"power\"}"
        }
      },
      "secondarySpecialSkills": []
    },
    "combat": {
      "attack": {
        "__type": "{\"type\":\"Ability\",\"attribute\":\"dexterity\"}",
        "base": {
          "value": 65
        }
      },
      "block": {
        "__type": "{\"type\":\"Ability\",\"attribute\":\"dexterity\"}"
      },
      "dodge": {
        "__type": "{\"type\":\"Ability\",\"attribute\":\"agility\"}",
        "base": {
          "value": 60
        }
      },
      "wearArmor": {
        "__type": "{\"type\":\"AffectedByCharacteristicValue\",\"attribute\":\"strength\"}",
        "base": {
          "value": 0
        }
      },
      "totalArmor": {
        "at": {
          "cut": {
            "value": 0
          },
          "impact": {
            "value": 0
          },
          "thrust": {
            "value": 0
          },
          "heat": {
            "value": 0
          },
          "electricity": {
            "value": 0
          },
          "cold": {
            "value": 0
          },
          "energy": {
            "value": 0
          }
        }
      },
      "combatSpecialSkills": [],
      "combatTables": [],
      "ammo": [],
      "weapons": [],
      "armors": [],
      "supernaturalShields": [],
      "damageReduction": {
        "__type": "{\"type\":\"NumericalValue\"}"
      }
    },
    "mystic": {
      "act": {
        "main": {
          "base": {
            "value": 0
          },
          "final": {
            "value": 0
          }
        },
        "via": []
      },
      "zeon": {
        "accumulated": 0,
        "value": 0,
        "max": 0
      },
      "zeonMaintained": {
        "value": 0,
        "max": 0
      },
      "zeonRegeneration": {
        "base": {
          "value": 0
        },
        "final": {
          "value": 0
        }
      },
      "innateMagic": {
        "main": {
          "base": {
            "value": 0
          },
          "final": {
            "value": 0
          }
        },
        "via": []
      },
      "magicProjection": {
        "base": {
          "value": 0
        },
        "final": {
          "value": 0
        },
        "imbalance": {
          "offensive": {
            "base": {
              "value": 0
            },
            "final": {
              "value": 0
            }
          },
          "defensive": {
            "base": {
              "value": 0
            },
            "final": {
              "value": 0
            }
          }
        }
      },
      "magicLevel": {
        "spheres": {
          "essence": {
            "value": 0
          },
          "water": {
            "value": 0
          },
          "earth": {
            "value": 0
          },
          "creation": {
            "value": 0
          },
          "darkness": {
            "value": 0
          },
          "necromancy": {
            "value": 0
          },
          "light": {
            "value": 0
          },
          "destruction": {
            "value": 0
          },
          "air": {
            "value": 0
          },
          "fire": {
            "value": 0
          },
          "illusion": {
            "value": 0
          }
        },
        "total": {
          "value": 0
        },
        "used": {
          "value": 0
        }
      },
      "summoning": {
        "summon": {
          "base": {
            "value": 0
          },
          "final": {
            "value": 0
          }
        },
        "banish": {
          "base": {
            "value": 0
          },
          "final": {
            "value": 0
          }
        },
        "bind": {
          "base": {
            "value": 0
          },
          "final": {
            "value": 0
          }
        },
        "control": {
          "base": {
            "value": 0
          },
          "final": {
            "value": 0
          }
        }
      },
      "mysticSettings": {
        "aptitudeForMagicDevelopment": false
      },
      "spells": [],
      "spellMaintenances": [],
      "selectedSpells": [],
      "summons": [],
      "metamagics": [],
      "preparedSpells": []
    },
    "domine": {
      "kiSkills": [],
      "nemesisSkills": [],
      "arsMagnus": [],
      "martialArts": [],
      "creatures": [],
      "specialSkills": [],
      "techniques": [],
      "seals": {
        "minor": {
          "fire": {
            "isActive": false
          },
          "metal": {
            "isActive": false
          },
          "wind": {
            "isActive": false
          },
          "water": {
            "isActive": false
          },
          "wood": {
            "isActive": false
          }
        },
        "major": {
          "fire": {
            "isActive": false
          },
          "metal": {
            "isActive": false
          },
          "wind": {
            "isActive": false
          },
          "water": {
            "isActive": false
          },
          "wood": {
            "isActive": false
          }
        }
      },
      "martialKnowledge": {
        "used": {
          "value": 0
        },
        "max": {
          "value": 0
        }
      },
      "kiAccumulation": {
        "strength": {
          "accumulated": {
            "value": 0
          },
          "base": {
            "value": 0
          },
          "final": {
            "value": 0
          }
        },
        "agility": {
          "accumulated": {
            "value": 0
          },
          "base": {
            "value": 0
          },
          "final": {
            "value": 0
          }
        },
        "dexterity": {
          "accumulated": {
            "value": 0
          },
          "base": {
            "value": 0
          },
          "final": {
            "value": 0
          }
        },
        "constitution": {
          "accumulated": {
            "value": 0
          },
          "base": {
            "value": 0
          },
          "final": {
            "value": 0
          }
        },
        "willPower": {
          "accumulated": {
            "value": 0
          },
          "base": {
            "value": 0
          },
          "final": {
            "value": 0
          }
        },
        "power": {
          "accumulated": {
            "value": 0
          },
          "base": {
            "value": 0
          },
          "final": {
            "value": 0
          }
        },
        "generic": {
          "value": 0,
          "max": 0
        }
      }
    },
    "psychic": {
      "psychicPotential": {
        "base": {
          "value": 0
        },
        "final": {
          "value": 0
        }
      },
      "psychicProjection": {
        "base": {
          "value": 0
        },
        "final": {
          "value": 0
        },
        "imbalance": {
          "offensive": {
            "base": {
              "value": 0
            },
            "final": {
              "value": 0
            }
          },
          "defensive": {
            "base": {
              "value": 0
            },
            "final": {
              "value": 0
            }
          }
        }
      },
      "psychicPoints": {
        "value": 0,
        "max": 0
      },
      "psychicSettings": {
        "fatigueResistance": false
      },
      "psychicPowers": [],
      "psychicDisciplines": [],
      "mentalPatterns": [],
      "innatePsychicPower": {
        "amount": {
          "value": 0
        }
      },
      "innatePsychicPowers": []
    }
  },
  "_stats": {
    "systemId": "animabf",
    "systemVersion": "2.2.1",
    "coreVersion": "14.359",
    "createdTime": null,
    "modifiedTime": null,
    "lastModifiedBy": null
  },
  "ownership": {
    "default": 0
  },
  "_key": "!actors!9e46a2f5b90703bf"
}
